{"clippedRows": 0, "hiddenValues": 0, "data": [{"count": 123769.0, "avg": 29.0, "value": "Children or Armed Forces"}, {"count": 40736.0, "avg": 38.0, "value": "Full-time schedules"}, {"count": 26808.0, "avg": 51.0, "value": "Not in labor force"}, {"count": 525.0, "avg": 38.0, "value": "PT for econ reasons usually FT"}, {"count": 1209.0, "avg": 41.0, "value": "PT for econ reasons usually PT"}, {"count": 3322.0, "avg": 39.0, "value": "PT for non-econ reasons usually FT"}, {"count": 2311.0, "avg": 34.0, "value": "Unemployed full-time"}, {"count": 843.0, "avg": 30.0, "value": "Unemployed part- time"}], "name": "fulltime"}