{"clippedRows": 0, "hiddenValues": 0, "data": [{"count": 14430.0, "avg": 25.0, "value": "Child 18 or older"}, {"count": 47.0, "avg": 15.0, "value": "Child under 18 ever married"}, {"count": 50426.0, "avg": 8.0, "value": "Child under 18 never married"}, {"count": 132.0, "avg": 44.0, "value": "Group Quarters- Secondary individual"}, {"count": 75475.0, "avg": 48.0, "value": "Householder"}, {"count": 7601.0, "avg": 29.0, "value": "Nonrelative of householder"}, {"count": 9703.0, "avg": 29.0, "value": "Other relative of householder"}, {"count": 41709.0, "avg": 45.0, "value": "Spouse of householder"}], "name": "household-simple"}